LICENSE
MANIFEST.in
README.rst
setup.cfg
setup.py
tpNameIt/__init__.py
tpNameIt/__logging__.ini
tpNameIt/__version__.py
tpNameIt/core/__init__.py
tpNameIt/core/nameit.py
tpNameIt/core/namelib.py
tpNameIt/data/NAMING_FILE_IS_CREATED_HERE_BY_DEFAULT
tpNameIt/resources/icons/color/rename.png
tpnameit.egg-info/PKG-INFO
tpnameit.egg-info/SOURCES.txt
tpnameit.egg-info/dependency_links.txt
tpnameit.egg-info/not-zip-safe
tpnameit.egg-info/requires.txt
tpnameit.egg-info/top_level.txt