Metadata-Version: 2.1
Name: tpnameit
Version: 0.0.14
Summary: Python module that manages the nomenclature of your pipelines.
Home-page: https://github.com/tpoveda/tpNameIt
Author: Tomas Poveda
Author-email: tpovedatd@gmail.com
License: MIT
Platform: UNKNOWN
Provides-Extra: dev
Provides-Extra: test
